treesort.py
treesort/__init__.py
treesort/cli.py
treesort/helpers.py
treesort/jc_outlier_detector.py
treesort/jc_reassortment_test.py
treesort/lm_outlier_detector.py
treesort/options.py
treesort/parsimony.py
treesort/reassortment_inference.py
treesort/reassortment_utils.py
treesort/tree_indexer.py
treesort/version.py
TreeSort-0.3.1.dist-info/LICENSE
TreeSort-0.3.1.dist-info/METADATA
TreeSort-0.3.1.dist-info/WHEEL
TreeSort-0.3.1.dist-info/entry_points.txt
TreeSort-0.3.1.dist-info/top_level.txt
TreeSort-0.3.1.dist-info/RECORD
