Metadata-Version: 2.1
Name: TreeSort
Version: 0.3.1
Summary: Virus reassortment inference software.Infers both recent and ancestral reassortment and uses flexible molecular clock constraints.
Home-page: https://github.com/flu-crew/TreeSort
Author: Alexey Markin
Author-email: alex.markin57@gmail.com
License: MIT
Classifier: Programming Language :: Python :: 3
Classifier: Programming Language :: Python :: 3.6
Classifier: Programming Language :: Python :: 3.7
Classifier: Programming Language :: Python :: 3.8
Classifier: Programming Language :: Python :: 3.9
Classifier: Programming Language :: Python :: 3.10
Classifier: Programming Language :: Python :: 3.11
Classifier: Programming Language :: Python :: 3.12
Classifier: Topic :: Scientific/Engineering :: Bio-Informatics
Classifier: License :: OSI Approved :: MIT License
Classifier: Operating System :: OS Independent
License-File: LICENSE
Requires-Dist: scipy>=1.7.0
Requires-Dist: biopython>=1.67
Requires-Dist: dendropy>=4.5.0
Requires-Dist: phylo-treetime>=0.9.4
Requires-Dist: matplotlib
